setup.py
T800/__init__.py
T800/winthread.py
T800.winthread.egg-info/PKG-INFO
T800.winthread.egg-info/SOURCES.txt
T800.winthread.egg-info/dependency_links.txt
T800.winthread.egg-info/top_level.txt