Metadata-Version: 1.1
Name: T800.winthread
Version: 2017.5.17
Summary: Extension of threading.Thread adding terminate method using Win32 API on Python
Home-page: https://github.com/sakurai-youhei/T800.winthread
Author: Youhei Sakurai
Author-email: sakurai.youhei@gmail.com
License: MIT
Keywords: Windows,Win32,ctypes,threading,Thread,threading.Thread,TerminatableThread,OpenThread,TerminateThread,CloseHandle
Platform: UNKNOWN
Classifier: License :: OSI Approved :: MIT License
Classifier: Development Status :: 4 - Beta
Classifier: Environment :: Win32 (MS Windows)
Classifier: Programming Language :: Python :: 2.7
Classifier: Programming Language :: Python :: 3.3
Classifier: Programming Language :: Python :: 3.4
Classifier: Programming Language :: Python :: 3.5
Classifier: Programming Language :: Python :: 3.6
Classifier: Operating System :: Microsoft :: Windows
Classifier: Intended Audience :: Developers
